trainerdex/api/__init__.py
trainerdex/api/base.py
trainerdex/api/client/__init__.py
trainerdex/api/client/base.py
trainerdex/api/client/token.py
trainerdex/api/exceptions.py
trainerdex/api/faction.py
trainerdex/api/http/__init__.py
trainerdex/api/http/auth/__init__.py
trainerdex/api/http/auth/decorators.py
trainerdex/api/http/auth/token.py
trainerdex/api/http/base.py
trainerdex/api/http/v1_calls.py
trainerdex/api/leaderboard.py
trainerdex/api/socialconnection.py
trainerdex/api/trainer.py
trainerdex/api/types/__init__.py
trainerdex/api/types/v1/__init__.py
trainerdex/api/types/v1/social_connection.py
trainerdex/api/types/v1/trainer.py
trainerdex/api/types/v1/update.py
trainerdex/api/types/v1/user.py
trainerdex/api/update.py
trainerdex/api/user.py
trainerdex/api/utils.py
trainerdex-4.0.3.dist-info/LICENSE
trainerdex-4.0.3.dist-info/WHEEL
trainerdex-4.0.3.dist-info/METADATA
trainerdex-4.0.3.dist-info/RECORD
