Metadata-Version: 2.1
Name: trainerdex
Version: 4.0.3
Summary: An API to interact with TrainerDex - a online database of Pokemon Go trainers
Home-page: https://trainerdex.app/
License: GPL-3.0
Author: Jay Turner
Author-email: jay@trainerdex.app
Requires-Python: >=3.8,<4.0
Classifier: Intended Audience :: Developers
Classifier: License :: OSI Approved :: GNU General Public License v3 (GPLv3)
Classifier: Operating System :: OS Independent
Classifier: Programming Language :: Python
Classifier: Programming Language :: Python :: 3
Classifier: Programming Language :: Python :: 3.8
Classifier: Programming Language :: Python :: 3.9
Classifier: Programming Language :: Python :: 3.10
Classifier: Programming Language :: Python :: 3.11
Classifier: Programming Language :: Python :: 3
Classifier: Programming Language :: Python :: 3 :: Only
Classifier: Programming Language :: Python :: 3.10
Classifier: Programming Language :: Python :: 3.8
Classifier: Programming Language :: Python :: 3.9
Classifier: Topic :: Software Development :: Libraries :: Python Modules
Requires-Dist: aiohttp (>=3.6.0,<4.0.0)
Requires-Dist: python-dateutil (>=2.8.1,<3.0.0)
Requires-Dist: typing-extensions (>=4.3.0,<5.0.0)
Project-URL: Repository, https://github.com/TrainerDex/TrainerDex.py
